humalab/__init__.py
humalab/constants.py
humalab/episode.py
humalab/humalab.py
humalab/humalab_api_client.py
humalab/humalab_config.py
humalab/humalab_test.py
humalab/run.py
humalab/utils.py
humalab/assets/__init__.py
humalab/assets/archive.py
humalab/assets/resource_operator.py
humalab/assets/files/__init__.py
humalab/assets/files/resource_file.py
humalab/assets/files/urdf_file.py
humalab/dists/__init__.py
humalab/dists/bernoulli.py
humalab/dists/categorical.py
humalab/dists/discrete.py
humalab/dists/distribution.py
humalab/dists/gaussian.py
humalab/dists/log_uniform.py
humalab/dists/truncated_gaussian.py
humalab/dists/uniform.py
humalab/metrics/__init__.py
humalab/metrics/code.py
humalab/metrics/metric.py
humalab/metrics/scenario_stats.py
humalab/metrics/summary.py
humalab/scenarios/__init__.py
humalab/scenarios/scenario.py
humalab/scenarios/scenario_operator.py
humalab/scenarios/scenario_test.py
humalab-0.1.3.dist-info/licenses/LICENSE
humalab-0.1.3.dist-info/METADATA
humalab-0.1.3.dist-info/WHEEL
humalab-0.1.3.dist-info/entry_points.txt
humalab-0.1.3.dist-info/top_level.txt
humalab-0.1.3.dist-info/RECORD
